{"description":"an event","title":"A title","cta":{"url":"#","text":"Register"},"tags":[{"tagCss":"css-class","tagName":"tag name"}],"type":"webinar","startDate":"2016-02-06","endDate":"2016-02-07","isAllDay":true}
{"description":"a second event","title":"A second title","cta":{"url":"#","text":"Register"},"tags":[{"tagCss":"css-class-2","tagName":"tag name 2"}],"type":"seminar","startDate":"2016-02-06","endDate":"2016-02-06","startTime":"10:00:00","endTime":"12:00:00","isAllDay":false}
{"description":"a second event","title":"A second title","cta":{"url":"#","text":"Register"},"tags":[{"tagCss":"css-class-2","tagName":"tag name 2"}],"type":"seminar","startDate":"2016-02-06","endDate":"2016-02-06","startTime":"13:00:00","endTime":"15:00:00","isAllDay":false}
{"description":"a third event","title":"A third title","cta":{"url":"#","text":"Register"},"tags":[{"tagCss":"css-class-third","tagName":"tag name third"}],"type":"seminar","startDate":"2016-02-07","endDate":"2016-02-07","isAllDay":true}
{"description":"a fourth event","title":"A fourth title","cta":{"url":"#","text":"Start Now"},"tags":[{"tagCss":"css-class-fourth","tagName":"tag name fourth"}],"type":"conference","startDate":"2016-02-08","endDate":"2016-02-08","startTime":"10:00:00","endTime":"13:00:00","isAllDay":false}
{"description":"a fourth event","title":"A fourth title","cta":{"url":"#","text":"Start Now"},"tags":[{"tagCss":"css-class-fifth","tagName":"tag name fifth"}],"type":"conference","startDate":"2016-02-09","endDate":"2016-02-09","startTime":"10:00:00","endTime":"13:00:00","isAllDay":false}
{"description":"a fifth event","title":"A fifth title","cta":{"url":"#","text":"Register Now"},"tags":[{"tagCss":"css-class-fifth","tagName":"tag name fifth"}],"type":"conference","startDate":"2016-02-10","endDate":"2016-02-10","startTime":"10:00:00","endTime":"13:00:00","isAllDay":false}
{"description":"a stacked event","title":"A fifth title","cta":{"url":"#","text":"Register Now"},"tags":[{"tagCss":"css-class-fifth","tagName":"tag name fifth"}],"type":"conference","startDate":"2016-02-09","endDate":"2016-02-10","startTime":"10:00:00","endTime":"13:00:00","isAllDay":false}
